wzmlx_dl/__init__.py
wzmlx_dl/anime_api.py
wzmlx_dl/processor.py
wzmlx_dl/utils.py
wzmlx_dl/static/N_m3u8DL-RE
wzmlx_dl/static/N_m3u8DL-RE.exe
wzmlx_dl/static/languages_info.json
wzmlx_dl-1.0.16.dist-info/LICENSE
wzmlx_dl-1.0.16.dist-info/METADATA
wzmlx_dl-1.0.16.dist-info/WHEEL
wzmlx_dl-1.0.16.dist-info/top_level.txt
wzmlx_dl-1.0.16.dist-info/RECORD
