Metadata-Version: 2.1
Name: wzmlx-dl
Version: 1.0.16
Summary: ZORO-DL - Download DUAL-AUDIO Multi SUBS Anime from ZORO
Author: weebzone
Author-email: doc.adhikari@gmail.com
Classifier: Programming Language :: Python :: 3
Classifier: Operating System :: OS Independent
Requires-Python: >=3.6
License-File: LICENSE
Requires-Dist: requests
Requires-Dist: beautifulsoup4
Requires-Dist: tenacity
Requires-Dist: yt-dlp
